tests/__init__.py
tests/test_thinkcellbuilder.py
thinkcellbuilder/__init__.py
thinkcellbuilder/thinkcellbuilder.py
ThinkcellBuilder-0.1.1.dist-info/LICENSE
ThinkcellBuilder-0.1.1.dist-info/METADATA
ThinkcellBuilder-0.1.1.dist-info/WHEEL
ThinkcellBuilder-0.1.1.dist-info/top_level.txt
ThinkcellBuilder-0.1.1.dist-info/RECORD
