Metadata-Version: 2.1
Name: ThinkcellBuilder
Version: 0.1.1
Summary: Simple unofficial Python library for generating PowerPoint presentations using Think-cell
Home-page: https://github.com/Philistino/ThinkcellBuilder
Author: Philistino
Author-email: philistino@protonmail.com
License: MIT
Project-URL: Bug Reports, https://github.com/Philistino/ThinkcellBuilder/issues
Project-URL: Source, https://github.com/Philistino/ThinkcellBuilder
Keywords: automation powerpoint thinkcell ppttc business consulting
Classifier: Programming Language :: Python :: 3.7
Classifier: Programming Language :: Python :: 3.8
Classifier: Programming Language :: Python :: 3.9
Classifier: Programming Language :: Python :: 3.10
Classifier: Programming Language :: Python :: 3.11
Classifier: License :: OSI Approved :: MIT License
Classifier: Operating System :: OS Independent
Requires-Python: >=3.7
License-File: LICENSE
